<?xml version="1.0" encoding="UTF-8" standalone="no" ?>
<multilingual-synset
  id="28840"
  xmlns="https://interslavic.fun/schemas/zonal-wordnet.xsd"
  xmlns:xsi="http://www.w3.org/2001/XMLSchema-instance"
  xmlns:steen="https://interslavic.fun/schemas/steenbergen.xsd"
>
  <synset lang="art-x-interslv">
    <lemma steen:id="28840" steen:pos="f." steen:type="1" steen:same="v j~">
      obmotka
    </lemma>
  </synset>
  <synset lang="en">
    <lemma>winding</lemma>
  </synset>
  <synset lang="be">
    <lemma>абмотка</lemma>
    <lemma>абмотванне</lemma>
  </synset>
  <synset lang="bg" verified="false">
    <lemma>ликвидация</lemma>
  </synset>
  <synset lang="cs">
    <lemma>vinutí</lemma>
  </synset>
  <synset lang="hr">
    <lemma>navoj</lemma>
  </synset>
  <synset lang="mk">
    <lemma>омот</lemma>
    <lemma>обвивка</lemma>
  </synset>
  <synset lang="pl">
    <lemma>uzwojenie</lemma>
  </synset>
  <synset lang="ru">
    <lemma>обмотка</lemma>
  </synset>
  <synset lang="sk">
    <lemma>vinutia</lemma>
  </synset>
  <synset lang="sl" verified="false">
    <lemma>nit navojak</lemma>
  </synset>
  <synset lang="sr">
    <lemma>навој</lemma>
    <lemma>навојак</lemma>
  </synset>
  <synset lang="uk">
    <lemma>обмотка</lemma>
  </synset>
  <synset lang="eo" verified="false">
    <lemma>serpentuma</lemma>
  </synset>
  <synset lang="de" verified="false">
    <lemma>Wickeln</lemma>
  </synset>
  <synset lang="nl">
    <lemma>wikkel</lemma>
  </synset>
</multilingual-synset>
