<?xml version="1.0" encoding="UTF-8" standalone="no" ?>
<multilingual-synset
  id="16265"
  xmlns="https://interslavic.fun/schemas/zonal-wordnet.xsd"
  xmlns:xsi="http://www.w3.org/2001/XMLSchema-instance"
  xmlns:steen="https://interslavic.fun/schemas/steenbergen.xsd"
>
  <synset lang="art-x-interslv">
    <lemma steen:id="16265" steen:pos="adj." steen:type="1" steen:genesis="I">
      astronomičny
    </lemma>
  </synset>
  <synset lang="en">
    <lemma>astronomical</lemma>
  </synset>
  <synset lang="be">
    <lemma>астранамічны</lemma>
  </synset>
  <synset lang="bg">
    <lemma>астрономически</lemma>
  </synset>
  <synset lang="cs">
    <lemma>astronomický</lemma>
  </synset>
  <synset lang="csb">
    <lemma>gvjôzdarskji</lemma>
  </synset>
  <synset lang="dsb">
    <lemma>astronomiski</lemma>
  </synset>
  <synset lang="hr">
    <lemma>astronomski</lemma>
  </synset>
  <synset lang="hsb">
    <lemma>astronomiski</lemma>
  </synset>
  <synset lang="mk">
    <lemma>астрономски</lemma>
  </synset>
  <synset lang="pl">
    <lemma>astronomiczny</lemma>
  </synset>
  <synset lang="ru">
    <lemma>астрономический</lemma>
  </synset>
  <synset lang="sk">
    <lemma>astronomický</lemma>
  </synset>
  <synset lang="sl">
    <lemma>astronomski</lemma>
  </synset>
  <synset lang="sr">
    <lemma>астрономски</lemma>
  </synset>
  <synset lang="uk">
    <lemma>астрономічний</lemma>
  </synset>
  <synset lang="eo" verified="false">
    <lemma>astronomiaj</lemma>
  </synset>
  <synset lang="es">
    <lemma>astronómico</lemma>
  </synset>
  <synset lang="fr" verified="false">
    <lemma>astronomique</lemma>
  </synset>
  <synset lang="it" verified="false">
    <lemma>astronomico</lemma>
  </synset>
  <synset lang="pt" verified="false">
    <lemma>astronômico</lemma>
  </synset>
  <synset lang="da" verified="false">
    <lemma>astronomiske</lemma>
  </synset>
  <synset lang="de">
    <lemma>astronomisch</lemma>
  </synset>
  <synset lang="nl">
    <lemma>astronomisch</lemma>
  </synset>
  <synset lang="he" verified="false">
    <lemma>אסטרונומי</lemma>
  </synset>
</multilingual-synset>
