<?xml version="1.0" encoding="UTF-8" standalone="no" ?>
<multilingual-synset
  id="10461"
  xmlns="https://interslavic.fun/schemas/zonal-wordnet.xsd"
  xmlns:xsi="http://www.w3.org/2001/XMLSchema-instance"
  xmlns:steen="https://interslavic.fun/schemas/steenbergen.xsd"
>
  <synset lang="art-x-interslv">
    <lemma steen:id="10461" steen:pos="m." steen:type="1">Veliky Pętȯk</lemma>
  </synset>
  <synset lang="en">
    <lemma>Good Friday</lemma>
  </synset>
  <synset lang="be">
    <lemma>Вялікая пятніца</lemma>
    <lemma>Страсная пятніца</lemma>
  </synset>
  <synset lang="bg">
    <lemma>Велики петък</lemma>
  </synset>
  <synset lang="cs">
    <lemma>Velký Pátek</lemma>
  </synset>
  <synset lang="dsb">
    <lemma>śichy pětk</lemma>
  </synset>
  <synset lang="hr">
    <lemma>Veliki petak</lemma>
  </synset>
  <synset lang="mk">
    <lemma>Велики Петок</lemma>
  </synset>
  <synset lang="pl">
    <lemma>Wielki Piątek</lemma>
  </synset>
  <synset lang="ru">
    <lemma>Страстная пятница</lemma>
  </synset>
  <synset lang="sk">
    <lemma>Veľký Piatok</lemma>
  </synset>
  <synset lang="sl" verified="false">
    <lemma>Dober petek</lemma>
  </synset>
  <synset lang="sr">
    <lemma>Велики Петак</lemma>
  </synset>
  <synset lang="uk">
    <lemma>
      Страсна п &apos; ятниця
    </lemma>
    <lemma>
      Стражденна п &apos; ятниця
    </lemma>
    <lemma>
      Велика п &apos; ятниця
    </lemma>
  </synset>
  <synset lang="eo" verified="false">
    <lemma>Sankta vendredo</lemma>
  </synset>
  <synset lang="es" verified="false">
    <lemma>Buen viernes</lemma>
  </synset>
  <synset lang="fr" verified="false">
    <lemma>Bon vendredi</lemma>
  </synset>
  <synset lang="it" verified="false">
    <lemma>Buon venerdì</lemma>
  </synset>
  <synset lang="pt" verified="false">
    <lemma>Boa sexta-feira</lemma>
  </synset>
  <synset lang="da" verified="false">
    <lemma>God fredag</lemma>
  </synset>
  <synset lang="de" verified="false">
    <lemma>Guter Freitag</lemma>
  </synset>
  <synset lang="nl">
    <lemma>Goede Vrijdag</lemma>
  </synset>
  <synset lang="he" verified="false">
    <lemma>שישי טוב</lemma>
  </synset>
</multilingual-synset>
