<?xml version="1.0" encoding="UTF-8" standalone="no" ?>
<multilingual-synset
  id="1041"
  xmlns="https://interslavic.fun/schemas/zonal-wordnet.xsd"
  xmlns:xsi="http://www.w3.org/2001/XMLSchema-instance"
  xmlns:steen="https://interslavic.fun/schemas/steenbergen.xsd"
>
  <synset lang="art-x-interslv">
    <lemma steen:id="1041" steen:pos="v.tr. pf." steen:type="1">
      råzměšati
    </lemma>
  </synset>
  <synset lang="en">
    <lemma>mix up</lemma>
  </synset>
  <synset lang="be">
    <lemma>размяшаць</lemma>
    <lemma>вымешаць</lemma>
    <lemma>змяшаць</lemma>
  </synset>
  <synset lang="bg">
    <lemma>размеся</lemma>
  </synset>
  <synset lang="cs">
    <lemma>rozmíchat</lemma>
    <lemma>zamíchat</lemma>
  </synset>
  <synset lang="hr">
    <lemma>pomiješati</lemma>
    <lemma>izmiješati</lemma>
  </synset>
  <synset lang="mk">
    <lemma>размеша</lemma>
    <lemma>измеша</lemma>
  </synset>
  <synset lang="pl">
    <lemma>rozmieszać</lemma>
    <lemma>zamieszać</lemma>
  </synset>
  <synset lang="ru">
    <lemma>размешать</lemma>
    <lemma>смешать</lemma>
  </synset>
  <synset lang="sk">
    <lemma>rozmiešať</lemma>
    <lemma>zamiešať</lemma>
  </synset>
  <synset lang="sl" verified="false">
    <lemma>mešana</lemma>
    <lemma>zmes</lemma>
    <lemma>pomešamo</lemma>
    <lemma>zmes</lemma>
  </synset>
  <synset lang="sr">
    <lemma>размешати</lemma>
    <lemma>помешати</lemma>
    <lemma>измешати</lemma>
    <lemma>смешати</lemma>
  </synset>
  <synset lang="uk">
    <lemma>розмішати</lemma>
    <lemma>змішати</lemma>
  </synset>
  <synset lang="eo" verified="false">
    <lemma>miksi supren</lemma>
  </synset>
  <synset lang="es" verified="false">
    <lemma>mezclar</lemma>
  </synset>
  <synset lang="fr" verified="false">
    <lemma>mélanger</lemma>
  </synset>
  <synset lang="it" verified="false">
    <lemma>mischiare</lemma>
  </synset>
  <synset lang="pt" verified="false">
    <lemma>misturar</lemma>
  </synset>
  <synset lang="da" verified="false">
    <lemma>Bland op</lemma>
  </synset>
  <synset lang="de" verified="false">
    <lemma>verwechseln</lemma>
  </synset>
  <synset lang="nl">
    <lemma>vermengen</lemma>
    <lemma>mixen</lemma>
  </synset>
  <synset lang="he" verified="false">
    <lemma>בִּלבּוּל</lemma>
  </synset>
</multilingual-synset>
