<?xml version="1.0" encoding="UTF-8" standalone="no" ?>
<multilingual-synset
  id="37065"
  xmlns="https://interslavic.fun/schemas/zonal-wordnet.xsd"
  xmlns:xsi="http://www.w3.org/2001/XMLSchema-instance"
  xmlns:steen="https://interslavic.fun/schemas/steenbergen.xsd"
>
  <synset lang="art-x-interslv">
    <lemma steen:id="37065" steen:pos="f.sg." steen:type="1" steen:same="v z j">
      Kama
    </lemma>
  </synset>
  <synset lang="en">
    <lemma>Kama</lemma>
  </synset>
  <synset lang="be">
    <lemma>Кама</lemma>
  </synset>
  <synset lang="bg">
    <lemma>Кама</lemma>
  </synset>
  <synset lang="cs">
    <lemma>Kama</lemma>
  </synset>
  <synset lang="hr">
    <lemma>Kama</lemma>
  </synset>
  <synset lang="mk">
    <lemma>Кама</lemma>
  </synset>
  <synset lang="pl">
    <lemma>Kama</lemma>
  </synset>
  <synset lang="ru">
    <lemma>Кама</lemma>
  </synset>
  <synset lang="sk">
    <lemma>Kama</lemma>
  </synset>
  <synset lang="sl">
    <lemma>Kama</lemma>
  </synset>
  <synset lang="sr">
    <lemma>Кама</lemma>
  </synset>
  <synset lang="uk">
    <lemma>Кама</lemma>
  </synset>
  <synset lang="eo" verified="false">
    <lemma>Kama</lemma>
  </synset>
  <synset lang="es" verified="false">
    <lemma>Kama</lemma>
  </synset>
  <synset lang="fr" verified="false">
    <lemma>Kama</lemma>
  </synset>
  <synset lang="it" verified="false">
    <lemma>Kama</lemma>
  </synset>
  <synset lang="pt" verified="false">
    <lemma>Kama</lemma>
  </synset>
  <synset lang="de">
    <lemma>Kama</lemma>
  </synset>
  <synset lang="nl">
    <lemma>Kama</lemma>
  </synset>
  <synset lang="he" verified="false">
    <lemma>קמא</lemma>
  </synset>
</multilingual-synset>
