<?xml version="1.0" encoding="UTF-8" standalone="no" ?>
<multilingual-synset
  id="3954"
  xmlns="https://interslavic.fun/schemas/zonal-wordnet.xsd"
  xmlns:xsi="http://www.w3.org/2001/XMLSchema-instance"
  xmlns:steen="https://interslavic.fun/schemas/steenbergen.xsd"
>
  <synset lang="art-x-interslv">
    <lemma steen:id="3954" steen:pos="v.tr. ipf." steen:type="1">
      vkladati
    </lemma>
  </synset>
  <synset lang="en">
    <lemma>contribute</lemma>
    <lemma>put in</lemma>
    <lemma>insert</lemma>
    <lemma>invest</lemma>
  </synset>
  <synset lang="be">
    <lemma>укладаць</lemma>
    <lemma>укладваць</lemma>
    <lemma>інвеставаць</lemma>
  </synset>
  <synset lang="bg">
    <lemma>допринасям</lemma>
    <lemma>влагам</lemma>
  </synset>
  <synset lang="cs">
    <lemma>vkládat</lemma>
    <lemma>investovat</lemma>
  </synset>
  <synset lang="hr">
    <lemma>ulagati</lemma>
    <lemma>investirati</lemma>
  </synset>
  <synset lang="hsb" verified="false">
    <lemma>inwestować</lemma>
    <lemma>zapołožować</lemma>
  </synset>
  <synset lang="mk">
    <lemma>вложува</lemma>
    <lemma>придонесува</lemma>
    <lemma>инвестира</lemma>
  </synset>
  <synset lang="pl">
    <lemma>wkładać</lemma>
    <lemma>inwestować</lemma>
    <lemma>dokładać się</lemma>
  </synset>
  <synset lang="ru">
    <lemma>вкладывать</lemma>
    <lemma>инвестировать</lemma>
  </synset>
  <synset lang="sk">
    <lemma>vkladať</lemma>
    <lemma>investovať</lemma>
  </synset>
  <synset lang="sl" verified="false">
    <lemma>vlagati</lemma>
  </synset>
  <synset lang="sr">
    <lemma>улагати</lemma>
    <lemma>давати допринос</lemma>
    <lemma>инвестирати</lemma>
  </synset>
  <synset lang="uk">
    <lemma>вкладати</lemma>
    <lemma>інвестувати</lemma>
  </synset>
  <synset lang="eo" verified="false">
    <lemma>kontribui</lemma>
    <lemma>metita en</lemma>
    <lemma>insert</lemma>
    <lemma>investas</lemma>
  </synset>
  <synset lang="es" verified="false">
    <lemma>contribuir</lemma>
    <lemma>puesto en</lemma>
    <lemma>insertar</lemma>
    <lemma>invertir</lemma>
  </synset>
  <synset lang="fr" verified="false">
    <lemma>contribuer</lemma>
    <lemma>mettre en</lemma>
    <lemma>insérer</lemma>
    <lemma>investir</lemma>
  </synset>
  <synset lang="it" verified="false">
    <lemma>contribuire</lemma>
    <lemma>messo in</lemma>
    <lemma>inserto</lemma>
    <lemma>investire</lemma>
  </synset>
  <synset lang="pt" verified="false">
    <lemma>contribuir</lemma>
    <lemma>colocar</lemma>
    <lemma>inserção</lemma>
    <lemma>investir</lemma>
  </synset>
  <synset lang="da" verified="false">
    <lemma>bidrage</lemma>
    <lemma>sat i</lemma>
    <lemma>indsætte</lemma>
    <lemma>investere</lemma>
  </synset>
  <synset lang="de" verified="false">
    <lemma>beitragen</lemma>
    <lemma>setzen in</lemma>
    <lemma>einfügen</lemma>
    <lemma>investieren</lemma>
  </synset>
  <synset lang="nl">
    <lemma>bijdragen</lemma>
    <lemma>inleggen</lemma>
    <lemma>investeren</lemma>
  </synset>
  <synset lang="he" verified="false">
    <lemma>לתרום</lemma>
    <lemma>לשים</lemma>
    <lemma>כנס</lemma>
    <lemma>להשקיע</lemma>
  </synset>
</multilingual-synset>
