<?xml version="1.0" encoding="UTF-8" standalone="no" ?>
<multilingual-synset
  id="36596"
  xmlns="https://interslavic.fun/schemas/zonal-wordnet.xsd"
  xmlns:xsi="http://www.w3.org/2001/XMLSchema-instance"
  xmlns:steen="https://interslavic.fun/schemas/steenbergen.xsd"
>
  <synset lang="art-x-interslv">
    <lemma
      steen:id="36596"
      steen:pos="v.intr. ipf."
      steen:type="1"
      steen:same="v z j"
    >
      mjaukati
    </lemma>
  </synset>
  <synset lang="en">
    <lemma>meow</lemma>
  </synset>
  <synset lang="be">
    <lemma>мяўкаць</lemma>
    <lemma>яўкаць</lemma>
  </synset>
  <synset lang="bg">
    <lemma>мяукам</lemma>
    <lemma>мяуча</lemma>
  </synset>
  <synset lang="cs">
    <lemma>mňoukat</lemma>
  </synset>
  <synset lang="hr">
    <lemma>mjaukati</lemma>
  </synset>
  <synset lang="mk">
    <lemma>мјаука</lemma>
  </synset>
  <synset lang="pl">
    <lemma>miauczeć</lemma>
  </synset>
  <synset lang="ru">
    <lemma>мяукать</lemma>
  </synset>
  <synset lang="sk">
    <lemma>mňaukať</lemma>
    <lemma>mňaučať</lemma>
  </synset>
  <synset lang="sl" verified="false">
    <lemma>mjaukati</lemma>
    <lemma>mnjaukati</lemma>
  </synset>
  <synset lang="sr">
    <lemma>мјаукати</lemma>
    <lemma>мњаукати</lemma>
  </synset>
  <synset lang="uk">
    <lemma>нявкати</lemma>
  </synset>
  <synset lang="eo" verified="false">
    <lemma>miaŭ</lemma>
  </synset>
  <synset lang="de" verified="false">
    <lemma>Miau</lemma>
  </synset>
  <synset lang="nl">
    <lemma>miauwen</lemma>
  </synset>
</multilingual-synset>
