<?xml version="1.0" encoding="UTF-8" standalone="no" ?>
<multilingual-synset
  id="16747"
  xmlns="https://interslavic.fun/schemas/zonal-wordnet.xsd"
  xmlns:xsi="http://www.w3.org/2001/XMLSchema-instance"
  xmlns:steen="https://interslavic.fun/schemas/steenbergen.xsd"
>
  <synset lang="art-x-interslv">
    <lemma steen:id="16747" steen:pos="f." steen:type="1" steen:same="v pl bg">
      maněrka
    </lemma>
  </synset>
  <synset lang="en">
    <lemma>flask</lemma>
  </synset>
  <synset lang="be">
    <lemma>фляжка</lemma>
    <lemma>тэрмас</lemma>
  </synset>
  <synset lang="bg">
    <lemma>манерка</lemma>
  </synset>
  <synset lang="cs">
    <lemma>čutora</lemma>
    <lemma>placatice</lemma>
    <lemma>polní flaška</lemma>
  </synset>
  <synset lang="hr">
    <lemma>čutura</lemma>
    <lemma>čuturica</lemma>
    <lemma>pljoska</lemma>
    <lemma>ploska</lemma>
  </synset>
  <synset lang="hsb" verified="false">
    <lemma>termoska</lemma>
  </synset>
  <synset lang="mk">
    <lemma>матарка</lemma>
  </synset>
  <synset lang="pl">
    <lemma>termos</lemma>
    <lemma>piersiówka</lemma>
  </synset>
  <synset lang="ru">
    <lemma>фляжка</lemma>
    <lemma>термос</lemma>
  </synset>
  <synset lang="sk">
    <lemma>poľná fľaška termoska</lemma>
    <lemma>fľaška</lemma>
  </synset>
  <synset lang="sl" verified="false">
    <lemma>Steklenica</lemma>
    <lemma>steklenica</lemma>
  </synset>
  <synset lang="sr">
    <lemma>чутура</lemma>
    <lemma>чутирица</lemma>
    <lemma>флашица</lemma>
  </synset>
  <synset lang="uk">
    <lemma>фляга</lemma>
    <lemma>фляжка</lemma>
    <lemma>термос</lemma>
  </synset>
  <synset lang="eo">
    <lemma>flakono</lemma>
  </synset>
  <synset lang="es" verified="false">
    <lemma>matraz</lemma>
  </synset>
  <synset lang="fr" verified="false">
    <lemma>ballon</lemma>
  </synset>
  <synset lang="it" verified="false">
    <lemma>borraccia</lemma>
  </synset>
  <synset lang="pt" verified="false">
    <lemma>frasco</lemma>
  </synset>
  <synset lang="da" verified="false">
    <lemma>kolbe</lemma>
  </synset>
  <synset lang="de" verified="false">
    <lemma>Flasche</lemma>
  </synset>
  <synset lang="nl">
    <lemma>heupfles</lemma>
  </synset>
  <synset lang="he" verified="false">
    <lemma>בקבוק</lemma>
  </synset>
</multilingual-synset>
