<?xml version="1.0" encoding="UTF-8" standalone="no" ?>
<multilingual-synset
  id="5949"
  xmlns="https://interslavic.fun/schemas/zonal-wordnet.xsd"
  xmlns:xsi="http://www.w3.org/2001/XMLSchema-instance"
  xmlns:steen="https://interslavic.fun/schemas/steenbergen.xsd"
>
  <synset lang="art-x-interslv">
    <lemma steen:id="5949" steen:pos="v.tr. ipf." steen:type="1">
      vȯzpominati
    </lemma>
  </synset>
  <synset lang="en">
    <lemma>commemorate</lemma>
    <lemma>recollect</lemma>
  </synset>
  <synset lang="be">
    <lemma>успамінаць</lemma>
    <lemma>памінаць</lemma>
    <lemma>згадваць</lemma>
    <lemma>спамінаць</lemma>
    <lemma>узгадваць</lemma>
    <lemma>прыгадваць</lemma>
    <lemma>прыпамінаць</lemma>
  </synset>
  <synset lang="bg">
    <lemma>възпоменавам</lemma>
    <lemma>отбелязвам</lemma>
  </synset>
  <synset lang="cs">
    <lemma>vzpomínat</lemma>
    <lemma>připomínat</lemma>
  </synset>
  <synset lang="hr" verified="false">
    <lemma annotation="npr. godišnjicu">obilježavati</lemma>
    <lemma>sjećati se</lemma>
  </synset>
  <synset lang="mk">
    <lemma>одбележува</lemma>
    <lemma>комеморира</lemma>
  </synset>
  <synset lang="pl">
    <lemma>upamiętniać</lemma>
    <lemma>przypominać sobie</lemma>
  </synset>
  <synset lang="ru">
    <lemma>поминать</lemma>
    <lemma>вспоминать</lemma>
    <lemma>припоминать</lemma>
  </synset>
  <synset lang="sk" verified="false">
    <lemma>spomínať</lemma>
    <lemma>pripomínať</lemma>
  </synset>
  <synset lang="sl" verified="false">
    <lemma annotation="npr. obletnica">označi</lemma>
    <lemma>da se spomnite</lemma>
  </synset>
  <synset lang="sr">
    <lemma annotation="нпр. годишњицу">обележавати</lemma>
    <lemma>сећати се</lemma>
  </synset>
  <synset lang="uk" verified="false">
    <lemma>поминати</lemma>
    <lemma>згадувати</lemma>
    <lemma>пригадувати</lemma>
  </synset>
  <synset lang="eo" verified="false">
    <lemma>festi</lemma>
    <lemma>memoras</lemma>
  </synset>
  <synset lang="es" verified="false">
    <lemma>conmemore</lemma>
    <lemma>recollect</lemma>
  </synset>
  <synset lang="fr" verified="false">
    <lemma>commémorent</lemma>
    <lemma>se souvenir</lemma>
  </synset>
  <synset lang="it" verified="false">
    <lemma>commemorate</lemma>
    <lemma>Rammentare</lemma>
  </synset>
  <synset lang="pt" verified="false">
    <lemma>comemorar</lemma>
    <lemma>recoleta</lemma>
  </synset>
  <synset lang="da" verified="false">
    <lemma>Mindes</lemma>
    <lemma>Recollect</lemma>
  </synset>
  <synset lang="de" verified="false">
    <lemma>gedenken</lemma>
    <lemma>erinnern</lemma>
  </synset>
  <synset lang="nl">
    <lemma>herdenken</lemma>
    <lemma>in de herinnering roepen</lemma>
  </synset>
  <synset lang="he" verified="false">
    <lemma>להנציח</lemma>
    <lemma>נזכר בו</lemma>
  </synset>
</multilingual-synset>
