<?xml version="1.0" encoding="UTF-8" standalone="no" ?>
<multilingual-synset
  id="20940"
  xmlns="https://interslavic.fun/schemas/zonal-wordnet.xsd"
  xmlns:xsi="http://www.w3.org/2001/XMLSchema-instance"
  xmlns:steen="https://interslavic.fun/schemas/steenbergen.xsd"
>
  <synset lang="art-x-interslv">
    <lemma steen:id="20940" steen:pos="v.tr. ipf." steen:type="1">
      odsuvati
    </lemma>
  </synset>
  <synset lang="en">
    <lemma>shove away</lemma>
    <lemma>push off</lemma>
  </synset>
  <synset lang="be">
    <lemma>адштурхваць</lemma>
    <lemma>адпіхаць</lemma>
    <lemma>адпхаць</lemma>
    <lemma>адтаўхваць</lemma>
    <lemma>аддаляць</lemma>
    <lemma>адціскаць</lemma>
  </synset>
  <synset lang="bg" verified="false">
    <lemma>набута далеч</lemma>
    <lemma>отблъскват</lemma>
  </synset>
  <synset lang="cs">
    <lemma>odsouvat</lemma>
  </synset>
  <synset lang="hr">
    <lemma>odguravati</lemma>
    <lemma>odgurivati</lemma>
  </synset>
  <synset lang="mk">
    <lemma>оттурнува</lemma>
    <lemma>оттргнува</lemma>
  </synset>
  <synset lang="pl">
    <lemma>odsuwać</lemma>
  </synset>
  <synset lang="ru">
    <lemma>отталкивать</lemma>
    <lemma>отодвигать</lemma>
    <lemma>оттеснять</lemma>
  </synset>
  <synset lang="sk">
    <lemma>odsúvať</lemma>
  </synset>
  <synset lang="sl" verified="false">
    <lemma>odriniti stran</lemma>
  </synset>
  <synset lang="sr">
    <lemma>одгуравати</lemma>
  </synset>
  <synset lang="uk">
    <lemma>відштовхувати</lemma>
    <lemma>відсовувати</lemma>
    <lemma>відтісняти</lemma>
  </synset>
  <synset lang="eo" verified="false">
    <lemma>baton for</lemma>
    <lemma>puŝi for</lemma>
  </synset>
  <synset lang="de" verified="false">
    <lemma>wegschieben</lemma>
    <lemma>abstoßen</lemma>
  </synset>
  <synset lang="nl">
    <lemma>wegschuiven</lemma>
  </synset>
</multilingual-synset>
