<?xml version="1.0" encoding="UTF-8" standalone="no" ?>
<multilingual-synset
  id="6979"
  xmlns="https://interslavic.fun/schemas/zonal-wordnet.xsd"
  xmlns:xsi="http://www.w3.org/2001/XMLSchema-instance"
  xmlns:steen="https://interslavic.fun/schemas/steenbergen.xsd"
>
  <synset lang="art-x-interslv">
    <lemma steen:id="6979" steen:pos="v.ipf." steen:type="1">
      davati råbotų
    </lemma>
  </synset>
  <synset lang="en">
    <lemma>hire</lemma>
    <lemma>employ</lemma>
  </synset>
  <synset lang="be">
    <lemma>наймаць</lemma>
    <lemma>працаўладкоўваць</lemma>
  </synset>
  <synset lang="bg">
    <lemma>наемам</lemma>
    <lemma>давам работа</lemma>
    <lemma>вземам на работа</lemma>
  </synset>
  <synset lang="cs">
    <lemma>najímat</lemma>
    <lemma>zaměstnávat</lemma>
    <lemma>dávat práci</lemma>
  </synset>
  <synset lang="hr">
    <lemma>unajmiti</lemma>
    <lemma>zaposliti</lemma>
  </synset>
  <synset lang="hsb" verified="false">
    <lemma>najimać</lemma>
  </synset>
  <synset lang="mk">
    <lemma>вработува</lemma>
    <lemma>дава работа</lemma>
  </synset>
  <synset lang="pl">
    <lemma>zatrudniać</lemma>
    <lemma>najmować</lemma>
    <lemma>dawać pracę</lemma>
  </synset>
  <synset lang="ru">
    <lemma>нанимать</lemma>
    <lemma>трудоустраивать</lemma>
  </synset>
  <synset lang="sk">
    <lemma>dávať prácu</lemma>
    <lemma>najímať</lemma>
    <lemma>zamestnávať</lemma>
  </synset>
  <synset lang="sl">
    <lemma>najemati</lemma>
  </synset>
  <synset lang="sr">
    <lemma>заппошљавати</lemma>
    <lemma>давати посао</lemma>
  </synset>
  <synset lang="uk">
    <lemma>наймати</lemma>
    <lemma>працевлаштовувати</lemma>
  </synset>
  <synset lang="eo" verified="false">
    <lemma>rekompencon por tio</lemma>
    <lemma>dungado</lemma>
  </synset>
  <synset lang="es" verified="false">
    <lemma>alquiler</lemma>
    <lemma>empleo</lemma>
  </synset>
  <synset lang="fr" verified="false">
    <lemma>location</lemma>
    <lemma>emploi</lemma>
  </synset>
  <synset lang="it" verified="false">
    <lemma>noleggio</lemma>
    <lemma>impiego</lemma>
  </synset>
  <synset lang="pt" verified="false">
    <lemma>aluguer</lemma>
    <lemma>empregam</lemma>
  </synset>
  <synset lang="da" verified="false">
    <lemma>leje</lemma>
    <lemma>ansætte</lemma>
  </synset>
  <synset lang="de" verified="false">
    <lemma>mieten</lemma>
    <lemma>beschäftigen</lemma>
  </synset>
  <synset lang="nl">
    <lemma>tewerkstellen</lemma>
    <lemma>in dienst nemen</lemma>
  </synset>
  <synset lang="he" verified="false">
    <lemma>לשכור</lemma>
    <lemma>להעסיק</lemma>
  </synset>
</multilingual-synset>
