<?xml version="1.0" encoding="UTF-8" standalone="no" ?>
<multilingual-synset
  id="36519"
  xmlns="https://interslavic.fun/schemas/zonal-wordnet.xsd"
  xmlns:xsi="http://www.w3.org/2001/XMLSchema-instance"
  xmlns:steen="https://interslavic.fun/schemas/steenbergen.xsd"
>
  <synset lang="art-x-interslv">
    <lemma steen:id="36519" steen:pos="f." steen:type="2" steen:same="ru uk bg">
      znamenitosť
    </lemma>
  </synset>
  <synset lang="en">
    <lemma>celebrity</lemma>
    <lemma>famous person</lemma>
  </synset>
  <synset lang="be">
    <lemma>знакамітасць</lemma>
    <lemma>славутасць</lemma>
    <lemma>выдатнасць</lemma>
  </synset>
  <synset lang="bg">
    <lemma>знаменитост</lemma>
    <lemma>известна личност</lemma>
  </synset>
  <synset lang="cs">
    <lemma>osobnost</lemma>
    <lemma>hvězda</lemma>
    <lemma>prominent</lemma>
    <lemma>celebrita</lemma>
  </synset>
  <synset lang="hr">
    <lemma>celebrity</lemma>
  </synset>
  <synset lang="mk">
    <lemma>славна личност</lemma>
    <lemma>позната личност</lemma>
  </synset>
  <synset lang="pl">
    <lemma>celebryt</lemma>
    <lemma>celebryta</lemma>
  </synset>
  <synset lang="ru">
    <lemma>знаменитость</lemma>
    <lemma>звезда</lemma>
  </synset>
  <synset lang="sk">
    <lemma>osobnosť</lemma>
    <lemma>hviezda</lemma>
    <lemma>prominent</lemma>
    <lemma>celebrita</lemma>
  </synset>
  <synset lang="sl" verified="false">
    <lemma>Celebrity</lemma>
  </synset>
  <synset lang="sr">
    <lemma>позната особа</lemma>
  </synset>
  <synset lang="uk">
    <lemma>знаменитість</lemma>
  </synset>
  <synset lang="eo" verified="false">
    <lemma>famulo</lemma>
    <lemma>fama persono</lemma>
  </synset>
  <synset lang="es" verified="false">
    <lemma>celebridad</lemma>
    <lemma>persona famosa</lemma>
  </synset>
  <synset lang="fr" verified="false">
    <lemma>célébrité</lemma>
    <lemma>personne célèbre</lemma>
  </synset>
  <synset lang="it" verified="false">
    <lemma>celebrità</lemma>
    <lemma>persona famosa</lemma>
  </synset>
  <synset lang="pt" verified="false">
    <lemma>celebridade</lemma>
    <lemma>pessoa famosa</lemma>
  </synset>
  <synset lang="da" verified="false">
    <lemma>berømthed</lemma>
    <lemma>berømt person</lemma>
  </synset>
  <synset lang="de" verified="false">
    <lemma>Berühmtheit</lemma>
  </synset>
  <synset lang="nl">
    <lemma>beroemdheid</lemma>
  </synset>
  <synset lang="he" verified="false">
    <lemma>סלבריטי</lemma>
    <lemma>אדם מפורסם</lemma>
  </synset>
</multilingual-synset>
