<?xml version="1.0" encoding="UTF-8" standalone="no" ?>
<multilingual-synset
  id="22713"
  xmlns="https://interslavic.fun/schemas/zonal-wordnet.xsd"
  xmlns:xsi="http://www.w3.org/2001/XMLSchema-instance"
  xmlns:steen="https://interslavic.fun/schemas/steenbergen.xsd"
>
  <synset lang="art-x-interslv">
    <lemma steen:id="22713" steen:pos="f." steen:type="2" steen:same="ru j">
      råzvråtnica
    </lemma>
  </synset>
  <synset lang="en">
    <lemma>slag</lemma>
    <lemma>whore</lemma>
    <lemma>slut</lemma>
  </synset>
  <synset lang="be">
    <lemma>распусніца</lemma>
    <lemma>раздура</lemma>
    <lemma>лайдачка</lemma>
    <lemma>блудніца</lemma>
    <lemma>бахурка</lemma>
    <lemma>курва</lemma>
  </synset>
  <synset lang="bg">
    <lemma>курва</lemma>
    <lemma>развратница</lemma>
  </synset>
  <synset lang="cs">
    <lemma>děvka</lemma>
    <lemma>kurva</lemma>
    <lemma>poběhlice</lemma>
    <lemma>běhna</lemma>
    <lemma>nevěstka</lemma>
  </synset>
  <synset lang="hr">
    <lemma>razvratnica</lemma>
    <lemma>bludnica</lemma>
    <lemma>razbludnica</lemma>
  </synset>
  <synset lang="mk">
    <lemma>развратница</lemma>
    <lemma>блудница</lemma>
    <lemma>курва</lemma>
  </synset>
  <synset lang="pl">
    <lemma>dziwka</lemma>
    <lemma>kurwa</lemma>
    <lemma>rozpustnica</lemma>
  </synset>
  <synset lang="ru">
    <lemma>развратница</lemma>
    <lemma>распутница</lemma>
    <lemma>блудница</lemma>
  </synset>
  <synset lang="sk">
    <lemma>kurva</lemma>
    <lemma>pobehlica</lemma>
    <lemma>cundra</lemma>
    <lemma>radodajka</lemma>
    <lemma>neviestka</lemma>
  </synset>
  <synset lang="sl">
    <lemma>razvratnica</lemma>
    <lemma>vlačuga</lemma>
    <lemma>kurba</lemma>
  </synset>
  <synset lang="sr">
    <lemma>развратница</lemma>
    <lemma>блудница</lemma>
    <lemma>дроља</lemma>
    <lemma>дроца</lemma>
  </synset>
  <synset lang="uk">
    <lemma>розпусниця</lemma>
    <lemma>збоченка</lemma>
    <lemma>блудниця</lemma>
  </synset>
  <synset lang="eo" verified="false">
    <lemma>skorio</lemma>
    <lemma>malcxastan slut</lemma>
  </synset>
  <synset lang="es" verified="false">
    <lemma>escoria</lemma>
    <lemma>puta</lemma>
    <lemma>puta</lemma>
  </synset>
  <synset lang="fr" verified="false">
    <lemma>scories</lemma>
    <lemma>pute</lemma>
    <lemma>salope</lemma>
  </synset>
  <synset lang="it" verified="false">
    <lemma>scorie</lemma>
    <lemma>puttana</lemma>
    <lemma>slut</lemma>
  </synset>
  <synset lang="pt" verified="false">
    <lemma>escória</lemma>
    <lemma>puta</lemma>
    <lemma>vagabunda</lemma>
  </synset>
  <synset lang="da" verified="false">
    <lemma>slagge</lemma>
    <lemma>hore</lemma>
    <lemma>tøs</lemma>
  </synset>
  <synset lang="de" verified="false">
    <lemma>Schlacke</lemma>
    <lemma>Hure</lemma>
    <lemma>Schlampe</lemma>
  </synset>
  <synset lang="nl">
    <lemma>slet</lemma>
    <lemma>slettebak</lemma>
  </synset>
  <synset lang="he" verified="false">
    <lemma>סיגים</lemma>
    <lemma>זונה</lemma>
    <lemma>שרמוטה</lemma>
  </synset>
</multilingual-synset>
