<?xml version="1.0" encoding="UTF-8" standalone="no" ?>
<multilingual-synset
  id="1834"
  xmlns="https://interslavic.fun/schemas/zonal-wordnet.xsd"
  xmlns:xsi="http://www.w3.org/2001/XMLSchema-instance"
  xmlns:steen="https://interslavic.fun/schemas/steenbergen.xsd"
>
  <synset lang="art-x-interslv">
    <lemma
      steen:id="1834"
      steen:pos="v.tr. ipf."
      steen:type="1"
      steen:same="v pl sh bm"
    >
      zabranjati
    </lemma>
  </synset>
  <synset lang="en">
    <lemma>forbid</lemma>
    <lemma>prohibit</lemma>
    <lemma>ban</lemma>
  </synset>
  <synset lang="be">
    <lemma>забараняць</lemma>
  </synset>
  <synset lang="bg">
    <lemma>забранявам</lemma>
  </synset>
  <synset lang="cs">
    <lemma>zakazovat</lemma>
  </synset>
  <synset lang="hr">
    <lemma>zabranjivati</lemma>
  </synset>
  <synset lang="hsb" verified="false">
    <lemma>zakazować</lemma>
    <lemma>zapowědować</lemma>
  </synset>
  <synset lang="mk">
    <lemma>забранува</lemma>
  </synset>
  <synset lang="pl">
    <lemma>zabraniać</lemma>
  </synset>
  <synset lang="ru">
    <lemma>запрещать</lemma>
    <lemma>воспрещать</lemma>
    <lemma annotation="устар.">возбранять</lemma>
  </synset>
  <synset lang="sk">
    <lemma>zakazovať</lemma>
  </synset>
  <synset lang="sl">
    <lemma>prepovedati</lemma>
  </synset>
  <synset lang="sr">
    <lemma>забрањивати</lemma>
  </synset>
  <synset lang="uk">
    <lemma>забороняти</lemma>
  </synset>
  <synset lang="eo" verified="false">
    <lemma>malpermesas</lemma>
    <lemma>malpermesi</lemma>
  </synset>
  <synset lang="es" verified="false">
    <lemma>prohibir</lemma>
    <lemma>prohibir</lemma>
  </synset>
  <synset lang="fr" verified="false">
    <lemma>interdire</lemma>
    <lemma>interdire</lemma>
  </synset>
  <synset lang="it" verified="false">
    <lemma>vietare</lemma>
    <lemma>vietare</lemma>
  </synset>
  <synset lang="pt" verified="false">
    <lemma>proibir</lemma>
    <lemma>proibir</lemma>
  </synset>
  <synset lang="da" verified="false">
    <lemma>forbyde</lemma>
    <lemma>forbyde</lemma>
  </synset>
  <synset lang="de" verified="false">
    <lemma>verbieten</lemma>
    <lemma>verbieten</lemma>
  </synset>
  <synset lang="nl">
    <lemma>verbieden</lemma>
  </synset>
  <synset lang="he" verified="false">
    <lemma>וחלילה</lemma>
    <lemma>לאסור</lemma>
  </synset>
</multilingual-synset>
