<?xml version="1.0" encoding="UTF-8" standalone="no" ?>
<multilingual-synset
  id="24070"
  xmlns="https://interslavic.fun/schemas/zonal-wordnet.xsd"
  xmlns:xsi="http://www.w3.org/2001/XMLSchema-instance"
  xmlns:steen="https://interslavic.fun/schemas/steenbergen.xsd"
>
  <synset lang="art-x-interslv">
    <lemma
      steen:id="24070"
      steen:pos="v.tr. ipf./pf."
      steen:type="1"
      steen:genesis="I"
    >
      adaptovati
    </lemma>
  </synset>
  <synset lang="be">
    <lemma>адаптаваць</lemma>
    <lemma>прыстасаваць</lemma>
  </synset>
  <synset lang="bg">
    <lemma>адаптирам</lemma>
    <lemma>пригаждам</lemma>
  </synset>
  <synset lang="cs">
    <lemma>adaptovat</lemma>
    <lemma>přizpůsobit</lemma>
  </synset>
  <synset lang="hr">
    <lemma>prilagoditi</lemma>
    <lemma>adaprirati</lemma>
  </synset>
  <synset lang="mk">
    <lemma>адаптира</lemma>
    <lemma>прилагодува</lemma>
  </synset>
  <synset lang="pl">
    <lemma>adaptować</lemma>
  </synset>
  <synset lang="ru">
    <lemma>адаптировать</lemma>
  </synset>
  <synset lang="sk">
    <lemma>adaptovať</lemma>
    <lemma>prispôsobiť</lemma>
  </synset>
  <synset lang="sl">
    <lemma annotation="se">prilagoditi</lemma>
    <lemma annotation="se">adaptirati</lemma>
  </synset>
  <synset lang="sr">
    <lemma>прилагодити</lemma>
  </synset>
  <synset lang="uk">
    <lemma>адаптувати</lemma>
  </synset>
  <synset lang="eo">
    <lemma>adapti</lemma>
  </synset>
  <synset lang="de">
    <lemma>anpassen</lemma>
  </synset>
  <synset lang="nl">
    <lemma>aanpassen</lemma>
  </synset>
</multilingual-synset>
