<?xml version="1.0" encoding="UTF-8" standalone="no" ?>
<multilingual-synset
  id="2509"
  xmlns="https://interslavic.fun/schemas/zonal-wordnet.xsd"
  xmlns:xsi="http://www.w3.org/2001/XMLSchema-instance"
  xmlns:steen="https://interslavic.fun/schemas/steenbergen.xsd"
>
  <synset lang="art-x-interslv">
    <lemma
      steen:id="2509"
      steen:addition="(vęže)"
      steen:pos="v.tr. ipf."
      steen:type="1"
    >
      vęzati
    </lemma>
  </synset>
  <synset lang="en">
    <lemma>bind</lemma>
    <lemma>connect</lemma>
    <lemma>tie</lemma>
  </synset>
  <synset lang="be">
    <lemma>вязаць</lemma>
    <lemma>звязваць</lemma>
  </synset>
  <synset lang="bg">
    <lemma>връзвам</lemma>
  </synset>
  <synset lang="cs">
    <lemma>vázat</lemma>
    <lemma>uvazovat</lemma>
    <lemma>svazovat</lemma>
    <lemma>zavazovat</lemma>
  </synset>
  <synset lang="cu">
    <lemma>вѧзати</lemma>
  </synset>
  <synset lang="hr">
    <lemma>vezivati</lemma>
  </synset>
  <synset lang="hsb" verified="false">
    <lemma>wjazać</lemma>
    <lemma>koplować</lemma>
    <lemma>zwjazować</lemma>
  </synset>
  <synset lang="mk">
    <lemma>врзува</lemma>
  </synset>
  <synset lang="pl">
    <lemma>wiązać</lemma>
    <lemma>powiązywać</lemma>
  </synset>
  <synset lang="ru">
    <lemma>вязать</lemma>
    <lemma>связывать</lemma>
  </synset>
  <synset lang="sk">
    <lemma>viazať</lemma>
    <lemma>zaväzovať</lemma>
    <lemma>zväzovať</lemma>
  </synset>
  <synset lang="sl" verified="false">
    <lemma>vezati</lemma>
  </synset>
  <synset lang="sr">
    <lemma>везати</lemma>
  </synset>
  <synset lang="uk">
    <lemma>
      в &apos; язати
    </lemma>
    <lemma>
      зв &apos; язувати
    </lemma>
  </synset>
  <synset lang="eo" verified="false">
    <lemma>ligos</lemma>
    <lemma>connect</lemma>
    <lemma>kravato</lemma>
  </synset>
  <synset lang="es" verified="false">
    <lemma>se unen</lemma>
    <lemma>de conexión</lemma>
    <lemma>corbata</lemma>
  </synset>
  <synset lang="fr" verified="false">
    <lemma>lier</lemma>
    <lemma>de connexion</lemma>
    <lemma>cravate</lemma>
  </synset>
  <synset lang="it" verified="false">
    <lemma>bind</lemma>
    <lemma>connect</lemma>
    <lemma>cravatta</lemma>
  </synset>
  <synset lang="pt" verified="false">
    <lemma>ligamento</lemma>
    <lemma>ligação</lemma>
    <lemma>laço</lemma>
  </synset>
  <synset lang="da" verified="false">
    <lemma>binder</lemma>
    <lemma>connect</lemma>
    <lemma>slips</lemma>
  </synset>
  <synset lang="de" verified="false">
    <lemma>binden</lemma>
    <lemma>verbinden</lemma>
    <lemma>binden</lemma>
  </synset>
  <synset lang="nl">
    <lemma>binden</lemma>
    <lemma>verbinden</lemma>
  </synset>
  <synset lang="he" verified="false">
    <lemma>לאגד</lemma>
    <lemma>Connect</lemma>
    <lemma>עניבה</lemma>
  </synset>
</multilingual-synset>
