<?xml version="1.0" encoding="UTF-8" standalone="no" ?>
<multilingual-synset
  id="4483"
  xmlns="https://interslavic.fun/schemas/zonal-wordnet.xsd"
  xmlns:xsi="http://www.w3.org/2001/XMLSchema-instance"
  xmlns:steen="https://interslavic.fun/schemas/steenbergen.xsd"
>
  <synset lang="art-x-interslv">
    <lemma steen:id="4483" steen:pos="v.tr. ipf." steen:type="1">uvažati</lemma>
  </synset>
  <synset lang="en">
    <lemma>honour</lemma>
    <lemma>pay respect</lemma>
    <lemma>pay tribute</lemma>
    <lemma>hold in esteem</lemma>
  </synset>
  <synset lang="be">
    <lemma>паважаць</lemma>
    <lemma>шанаваць</lemma>
  </synset>
  <synset lang="bg">
    <lemma>уважавам</lemma>
  </synset>
  <synset lang="cs">
    <lemma>vážit si</lemma>
    <lemma>držet v úctě</lemma>
  </synset>
  <synset lang="csb">
    <lemma>òpasowac</lemma>
  </synset>
  <synset lang="hr">
    <lemma>poštovati</lemma>
    <lemma>štovati</lemma>
    <lemma>uvažavati</lemma>
    <lemma>cijeniti</lemma>
  </synset>
  <synset lang="mk">
    <lemma>уважува</lemma>
  </synset>
  <synset lang="pl">
    <lemma>poważać</lemma>
    <lemma>honorować</lemma>
    <lemma>darzyć szacunkiem</lemma>
  </synset>
  <synset lang="ru">
    <lemma>уважать</lemma>
    <lemma>почитать</lemma>
  </synset>
  <synset lang="sk">
    <lemma>vážiť si</lemma>
    <lemma>držať v úcte</lemma>
  </synset>
  <synset lang="sl" verified="false">
    <lemma>spoštovati</lemma>
    <lemma>priznana</lemma>
    <lemma>spoštovana</lemma>
  </synset>
  <synset lang="sr">
    <lemma>поштовати</lemma>
    <lemma>признавати</lemma>
    <lemma>уважавати</lemma>
  </synset>
  <synset lang="uk">
    <lemma>поважати</lemma>
    <lemma>шанувати</lemma>
  </synset>
  <synset lang="eo" verified="false">
    <lemma>honoro</lemma>
    <lemma>salajro respekton</lemma>
    <lemma>omaĝas</lemma>
    <lemma>kunigitaj kun estimon</lemma>
  </synset>
  <synset lang="es" verified="false">
    <lemma>el honor</lemma>
    <lemma>el respeto de pago</lemma>
    <lemma>paga las dos dracmas</lemma>
    <lemma>retención en la estima</lemma>
  </synset>
  <synset lang="fr" verified="false">
    <lemma>honneur</lemma>
    <lemma>le respect de la rémunération</lemma>
    <lemma>rendent hommage</lemma>
    <lemma>
      beaucoup d &apos; estime
    </lemma>
  </synset>
  <synset lang="it" verified="false">
    <lemma>onore</lemma>
    <lemma>il rispetto retribuzione</lemma>
    <lemma>rendono omaggio</lemma>
    <lemma>tenere in considerazione</lemma>
  </synset>
  <synset lang="pt" verified="false">
    <lemma>honra</lemma>
    <lemma>respeito do pagamento</lemma>
    <lemma>prestar homenagem</lemma>
    <lemma>espera na estima</lemma>
  </synset>
  <synset lang="da" verified="false">
    <lemma>ære</lemma>
    <lemma>løn respekt</lemma>
    <lemma>hylde</lemma>
    <lemma>fat i agtelse</lemma>
  </synset>
  <synset lang="de" verified="false">
    <lemma>Ehre</lemma>
    <lemma>Respekt zollen</lemma>
    <lemma>zahlen Tribut</lemma>
    <lemma>halten in Wertschätzung</lemma>
  </synset>
  <synset lang="nl">
    <lemma>hoogachten</lemma>
    <lemma>respecteren</lemma>
    <lemma>eer bewijzen</lemma>
  </synset>
  <synset lang="he" verified="false">
    <lemma>כבוד</lemma>
    <lemma>כבוד לשלם</lemma>
    <lemma>לחלוק כבוד</lemma>
    <lemma>אחיזה הערכה</lemma>
  </synset>
</multilingual-synset>
