<?xml version="1.0" encoding="UTF-8" standalone="no" ?>
<multilingual-synset
  id="22766"
  xmlns="https://interslavic.fun/schemas/zonal-wordnet.xsd"
  xmlns:xsi="http://www.w3.org/2001/XMLSchema-instance"
  xmlns:steen="https://interslavic.fun/schemas/steenbergen.xsd"
>
  <synset lang="art-x-interslv">
    <lemma steen:id="22766" steen:pos="adj." steen:type="1">pakistansky</lemma>
  </synset>
  <synset lang="en">
    <lemma>Pakistani</lemma>
  </synset>
  <synset lang="be">
    <lemma>пакістанская</lemma>
    <lemma>пакістанскі</lemma>
  </synset>
  <synset lang="bg" verified="false">
    <lemma>Пакистански</lemma>
  </synset>
  <synset lang="cs">
    <lemma>pákistánský</lemma>
  </synset>
  <synset lang="hr">
    <lemma>pakistanski</lemma>
  </synset>
  <synset lang="mk">
    <lemma>пакистански</lemma>
  </synset>
  <synset lang="pl">
    <lemma>pakistański</lemma>
  </synset>
  <synset lang="ru">
    <lemma>пакистанский</lemma>
  </synset>
  <synset lang="sk" verified="false">
    <lemma>pakistanský</lemma>
  </synset>
  <synset lang="sl" verified="false">
    <lemma>pakistanski</lemma>
  </synset>
  <synset lang="sr">
    <lemma>пакистански</lemma>
  </synset>
  <synset lang="uk">
    <lemma>пакистанський</lemma>
  </synset>
  <synset lang="eo" verified="false">
    <lemma>pakistana</lemma>
  </synset>
  <synset lang="de" verified="false">
    <lemma>pakistanisch</lemma>
  </synset>
  <synset lang="nl">
    <lemma>Pakistaans</lemma>
  </synset>
</multilingual-synset>
