<?xml version="1.0" encoding="UTF-8" standalone="no" ?>
<multilingual-synset
  id="176"
  xmlns="https://interslavic.fun/schemas/zonal-wordnet.xsd"
  xmlns:xsi="http://www.w3.org/2001/XMLSchema-instance"
  xmlns:steen="https://interslavic.fun/schemas/steenbergen.xsd"
>
  <synset lang="art-x-interslv">
    <lemma steen:id="176" steen:pos="adj." steen:type="1">kašubsky</lemma>
  </synset>
  <synset lang="en">
    <lemma>Kashubian</lemma>
    <lemma>Cashubian</lemma>
  </synset>
  <synset lang="be">
    <lemma>кашубскі</lemma>
  </synset>
  <synset lang="bg">
    <lemma>кашубски</lemma>
  </synset>
  <synset lang="cs">
    <lemma>kašubský</lemma>
  </synset>
  <synset lang="csb">
    <lemma>kaszëbsczi</lemma>
  </synset>
  <synset lang="hr">
    <lemma>kašupski</lemma>
  </synset>
  <synset lang="mk">
    <lemma>кашубиски</lemma>
  </synset>
  <synset lang="pl">
    <lemma>kaszubski</lemma>
  </synset>
  <synset lang="ru">
    <lemma>кашубский</lemma>
  </synset>
  <synset lang="sk">
    <lemma>kašubský</lemma>
  </synset>
  <synset lang="sl" verified="false">
    <lemma>kašubščina</lemma>
  </synset>
  <synset lang="sr">
    <lemma>кашупски</lemma>
  </synset>
  <synset lang="uk">
    <lemma>кашубський</lemma>
  </synset>
  <synset lang="eo" verified="false">
    <lemma>Kaŝuba</lemma>
    <lemma>Cashubian</lemma>
  </synset>
  <synset lang="es" verified="false">
    <lemma>Casubio</lemma>
    <lemma>Cashubian</lemma>
  </synset>
  <synset lang="fr" verified="false">
    <lemma>Kashubian</lemma>
    <lemma>Cashubian</lemma>
  </synset>
  <synset lang="it" verified="false">
    <lemma>Kashubian</lemma>
    <lemma>Cashubian</lemma>
  </synset>
  <synset lang="pt" verified="false">
    <lemma>Kashubian</lemma>
    <lemma>Cashubian</lemma>
  </synset>
  <synset lang="da" verified="false">
    <lemma>Kasjubisk</lemma>
    <lemma>Cashubian</lemma>
  </synset>
  <synset lang="de" verified="false">
    <lemma>Kaschubische</lemma>
    <lemma>Cashubian</lemma>
  </synset>
  <synset lang="nl">
    <lemma>Kasjoebisch</lemma>
  </synset>
  <synset lang="he" verified="false">
    <lemma>Kashubian</lemma>
    <lemma>Cashubian</lemma>
  </synset>
</multilingual-synset>
